Metadata-Version: 1.0
Name: ccq18-hello
Version: 0.1.1
Summary: demos
Home-page: UNKNOWN
Author: ccq18
Author-email: 348578429@qq.com
License: MIT
Platform: UNKNOWN
